LICENSE
nannernest/__init__.py
nannernest/__main__.py
nannernest/cli.py
nannernest/exceptions.py
nannernest/nesting.py
nannernest/segmentation.py
nannernest/slices.py
nannernest/slicing.py
nannernest/viz.py
nannernest-0.1.4.dist-info/entry_points.txt
nannernest-0.1.4.dist-info/LICENSE
nannernest-0.1.4.dist-info/WHEEL
nannernest-0.1.4.dist-info/METADATA
nannernest-0.1.4.dist-info/RECORD
