Metadata-Version: 2.1
Name: nannernest
Version: 0.1.4
Summary: Optimal peanut butter and banana sandwiches
Home-page: https://github.com/EthanRosenthal/nannernest
Keywords: deep learning,machine learning,peanut butter,banana,sandwich
Author: Ethan Rosenthal
Author-email: ethan@ethanrosenthal.com
Requires-Python: >=3.7,<4.0
Classifier: Development Status :: 3 - Alpha
Classifier: License :: OSI Approved :: GNU Affero General Public License v3
Classifier: Programming Language :: Python :: 3
Classifier: Programming Language :: Python :: 3 :: Only
Classifier: Programming Language :: Python :: 3.7
Classifier: Programming Language :: Python :: 3.8
Requires-Dist: Pillow (>=7.2.0,<8.0.0)
Requires-Dist: click-spinner (>=0.1.10,<0.2.0)
Requires-Dist: colorama (>=0.4.3,<0.5.0)
Requires-Dist: matplotlib (>=3.3.0,<4.0.0)
Requires-Dist: nest2D (==0.4.3)
Requires-Dist: numpy (>=1.19.1,<2.0.0)
Requires-Dist: scikit-image (>=0.17.2,<0.18.0)
Requires-Dist: scipy (>=1.5.2,<2.0.0)
Requires-Dist: seaborn (>=0.10.1,<0.11.0)
Requires-Dist: svgpath2mpl (>=0.2.1,<0.3.0)
Requires-Dist: sympy (>=1.6.1,<2.0.0)
Requires-Dist: torch (>=1.6.0,<2.0.0)
Requires-Dist: torchvision (>=0.7.0,<0.8.0)
Requires-Dist: typer (>=0.3.1,<0.4.0)
Project-URL: Repository, https://github.com/EthanRosenthal/nannernest
